pyquantize/__init__.py
pyquantize/quantize.py
pyquantize/quantize_grid.py
pyquantize/quantize_set.py
pyquantize-0.2.0.dist-info/licenses/LICENSE
pyquantize-0.2.0.dist-info/METADATA
pyquantize-0.2.0.dist-info/WHEEL
pyquantize-0.2.0.dist-info/top_level.txt
pyquantize-0.2.0.dist-info/RECORD
