Metadata-Version: 2.4
Name: pyquantize
Version: 0.2.0
Summary: numerical quantization
Author-email: deftasparagusanaconda <deftasparagusanaconda@gmail.com>
License-Expression: GPL-3.0-or-later
Project-URL: Homepage, https://github.com/deftasparagusanaconda/pyquantize
Project-URL: Repository, https://github.com/deftasparagusanaconda/pyquantize
Project-URL: Documentation, https://github.com/deftasparagusanaconda/pyquantize#readme
Keywords: quantize,quantization,rounding,stochastic,python,math
Classifier: Programming Language :: Python :: 3
Classifier: Operating System :: OS Independent
Requires-Python: >=3.6.0
License-File: LICENSE
Dynamic: license-file
